odoo/addons/connector_jira/README.rst
odoo/addons/connector_jira/__init__.py
odoo/addons/connector_jira/__manifest__.py
odoo/addons/connector_jira/fields.py
odoo/addons/connector_jira/cli/__init__.py
odoo/addons/connector_jira/cli/jira_oauth_dance.py
odoo/addons/connector_jira/components/__init__.py
odoo/addons/connector_jira/components/backend_adapter.py
odoo/addons/connector_jira/components/base.py
odoo/addons/connector_jira/components/binder.py
odoo/addons/connector_jira/components/exporter.py
odoo/addons/connector_jira/components/importer.py
odoo/addons/connector_jira/components/mapper.py
odoo/addons/connector_jira/controllers/__init__.py
odoo/addons/connector_jira/controllers/main.py
odoo/addons/connector_jira/data/cron.xml
odoo/addons/connector_jira/demo/jira_backend_demo.xml
odoo/addons/connector_jira/i18n/connector_jira.pot
odoo/addons/connector_jira/models/__init__.py
odoo/addons/connector_jira/models/account_analytic_line/__init__.py
odoo/addons/connector_jira/models/account_analytic_line/common.py
odoo/addons/connector_jira/models/account_analytic_line/deleter.py
odoo/addons/connector_jira/models/account_analytic_line/importer.py
odoo/addons/connector_jira/models/jira_backend/__init__.py
odoo/addons/connector_jira/models/jira_backend/common.py
odoo/addons/connector_jira/models/jira_binding/__init__.py
odoo/addons/connector_jira/models/jira_binding/common.py
odoo/addons/connector_jira/models/jira_issue_type/__init__.py
odoo/addons/connector_jira/models/jira_issue_type/common.py
odoo/addons/connector_jira/models/jira_issue_type/importer.py
odoo/addons/connector_jira/models/project_project/__init__.py
odoo/addons/connector_jira/models/project_project/binder.py
odoo/addons/connector_jira/models/project_project/common.py
odoo/addons/connector_jira/models/project_project/exporter.py
odoo/addons/connector_jira/models/project_project/project_link_jira.py
odoo/addons/connector_jira/models/project_task/__init__.py
odoo12_addon_connector_jira-12.0.1.7.0.dist-info/METADATA
odoo12_addon_connector_jira-12.0.1.7.0.dist-info/WHEEL
odoo12_addon_connector_jira-12.0.1.7.0.dist-info/top_level.txt
odoo12_addon_connector_jira-12.0.1.7.0.dist-info/RECORD
