Metadata-Version: 2.1
Name: odoo12-addon-connector-jira
Version: 12.0.1.7.0
Summary: JIRA Connector
Home-page: https://github.com/OCA/connector-jira
Author: Camptocamp,Odoo Community Association (OCA)
Author-email: support@odoo-community.org
License: AGPL-3
Platform: UNKNOWN
Classifier: Programming Language :: Python
Classifier: Framework :: Odoo
Classifier: License :: OSI Approved :: GNU Affero General Public License v3
Requires-Python: >=3.5
Requires-Dist: cryptography
Requires-Dist: jira
Requires-Dist: oauthlib
Requires-Dist: odoo12-addon-connector
Requires-Dist: odoo12-addon-multi-step-wizard
Requires-Dist: odoo12-addon-queue-job
Requires-Dist: odoo12-addon-web-widget-url-advanced
Requires-Dist: odoo (<12.1dev,>=12.0a)
Requires-Dist: requests
